intel_extension_for_deepspeed/__init__.py
intel_extension_for_deepspeed/xpu_accelerator.py
intel_extension_for_deepspeed/op_builder/__init__.py
intel_extension_for_deepspeed/op_builder/async_io.py
intel_extension_for_deepspeed/op_builder/builder.py
intel_extension_for_deepspeed/op_builder/cpu_adagrad.py
intel_extension_for_deepspeed/op_builder/cpu_adam.py
intel_extension_for_deepspeed/op_builder/flash_attn.py
intel_extension_for_deepspeed/op_builder/fused_adam.py
intel_extension_for_deepspeed/op_builder/quantizer.py
intel_extension_for_deepspeed/op_builder/transformer_inference.py
intel_extension_for_deepspeed/op_builder/utils.py
intel_extension_for_deepspeed/op_builder/csrc/adagrad/cpu_adagrad.cpp
intel_extension_for_deepspeed/op_builder/csrc/adam/cpu_adam.cpp
intel_extension_for_deepspeed/op_builder/csrc/adam/cpu_adam_impl.cpp
intel_extension_for_deepspeed/op_builder/csrc/adam/fused_adam_frontend.cpp
intel_extension_for_deepspeed/op_builder/csrc/adam/multi_tensor_adam.dp.cpp
intel_extension_for_deepspeed/op_builder/csrc/adam/multi_tensor_apply.dp.hpp
intel_extension_for_deepspeed/op_builder/csrc/common/custom_cuda_kernel.dp.cpp
intel_extension_for_deepspeed/op_builder/csrc/flash_attn/flash_attn.dp.cpp
intel_extension_for_deepspeed/op_builder/csrc/flash_attn/flash_attn_bwd.cpp
intel_extension_for_deepspeed/op_builder/csrc/flash_attn/flash_attn_fwd.cpp
intel_extension_for_deepspeed/op_builder/csrc/includes/dpct/atomic.hpp
intel_extension_for_deepspeed/op_builder/csrc/includes/dpct/blas_utils.hpp
intel_extension_for_deepspeed/op_builder/csrc/includes/dpct/ccl_utils.hpp
intel_extension_for_deepspeed/op_builder/csrc/includes/dpct/device.hpp
intel_extension_for_deepspeed/op_builder/csrc/includes/dpct/dnnl_utils.hpp
intel_extension_for_deepspeed/op_builder/csrc/includes/dpct/dpct.hpp
intel_extension_for_deepspeed/op_builder/csrc/includes/dpct/dpl_utils.hpp
intel_extension_for_deepspeed/op_builder/csrc/includes/dpct/fft_utils.hpp
intel_extension_for_pytorch_deepspeed-0.0.1.dist-info/LICENSE
intel_extension_for_pytorch_deepspeed-0.0.1.dist-info/METADATA
intel_extension_for_pytorch_deepspeed-0.0.1.dist-info/WHEEL
intel_extension_for_pytorch_deepspeed-0.0.1.dist-info/top_level.txt
intel_extension_for_pytorch_deepspeed-0.0.1.dist-info/RECORD
