Metadata-Version: 2.1
Name: intel_extension_for_pytorch_deepspeed
Version: 0.0.1
Summary: Intel® Extension for DeepSpeed*
Home-page: https://github.com/intel/intel-extension-for-deepspeed
Author: Intel Corporation
License: https://opensource.org/license/mit
License-File: LICENSE
Requires-Dist: setuptools
